wizz/__init__.py
wizz/__main__.py
wizz/agent/__init__.py
wizz/agent/chat.py
wizz/agent/retriever.py
wizz/app.py
wizz/commands/__init__.py
wizz/commands/knowledge.py
wizz/constants.py
wizz/crud.py
wizz/database.py
wizz/extraction/__init__.py
wizz/extraction/batcher.py
wizz/extraction/constants.py
wizz/extraction/converters.py
wizz/extraction/embedder.py
wizz/extraction/outlier_finder.py
wizz/filesystem.py
wizz/interface/__init__.py
wizz/interface/enums.py
wizz/interface/schemas.py
wizz/interface/types.py
wizz/models/__init__.py
wizz/models/base.py
wizz/models/knowledge.py
wizz/syncer.py
wizz-0.2.2.dist-info/LICENSE
wizz-0.2.2.dist-info/METADATA
wizz-0.2.2.dist-info/WHEEL
wizz-0.2.2.dist-info/entry_points.txt
wizz-0.2.2.dist-info/RECORD
